ssv/__init__.py
ssv/constant.py
ssv/exception.py
ssv/reader.py
ssv/writer.py
ssv-0.1.1.dist-info/DESCRIPTION.rst
ssv-0.1.1.dist-info/METADATA
ssv-0.1.1.dist-info/RECORD
ssv-0.1.1.dist-info/WHEEL
ssv-0.1.1.dist-info/metadata.json
ssv-0.1.1.dist-info/top_level.txt
